obsiasset/__init__.py
obsiasset/main.py
obsiasset/cli/__init__.py
obsiasset/cli/appApi.py
obsiasset/cli/appCli.py
obsiasset/config/app.yaml
obsiasset/i18n/sales_cn.yaml
obsiasset/i18n/sales_en.yaml
obsiasset/sample/sales_contact.md.j2
obsiasset/sample/sales_customer.md.j2
obsiasset/sample/sales_meeting_notes.md.j2
obsiasset/sample/sales_product.md.j2
obsiasset/sample/sales_project.md.j2
obsiasset/schema/sales.yaml.j2
obsiasset/tmpl/sales_contact.md.j2
obsiasset/tmpl/sales_custom_properties.md.j2
obsiasset/tmpl/sales_customer.md.j2
obsiasset/tmpl/sales_meeting_notes.md.j2
obsiasset/tmpl/sales_product.md.j2
obsiasset/tmpl/sales_project.md.j2
obsiasset/tmpl/sales_project_board.base.j2
obsiasset/tmpl/sales_task_list.md.j2
obsiasset/utils/__init__.py
obsiasset/utils/appConfig.py
obsiasset/utils/appLogger.py
obsiasset/utils/appManager.py
obsiasset-0.1.3.dist-info/licenses/LICENSE
obsiasset-0.1.3.dist-info/METADATA
obsiasset-0.1.3.dist-info/WHEEL
obsiasset-0.1.3.dist-info/entry_points.txt
obsiasset-0.1.3.dist-info/top_level.txt
obsiasset-0.1.3.dist-info/RECORD
