Metadata-Version: 2.4
Name: obsiasset
Version: 0.1.3
Summary: Obsidian Asset Manager
Author-email: Will <bxwill.shi@gmail.com>
Maintainer-email: Will <bxwill.shi@gmail.com>
Project-URL: Homepage, https://github.com/bxwillshi/obsidian-asset-manager
Keywords: obsidian,vault,asset,cli,manage
Classifier: Programming Language :: Python :: 3
Classifier: Operating System :: Microsoft :: Windows
Classifier: Operating System :: POSIX :: Linux
Classifier: Operating System :: MacOS :: MacOS X
Requires-Python: >=3.7
License-File: LICENSE
Requires-Dist: PyYAML
Requires-Dist: tabulate
Requires-Dist: requests
Requires-Dist: argcomplete
Requires-Dist: jinja2
Dynamic: license-file
